[{"Game Date": "2022-04-12", "Pitcher": "Baker, Bryan", "Result": "grounded_into_double_play", "EV (MPH)": "82.4", "LA (\u00b0)": "-23", "Dist (ft)": "4", "Direction": "Pull", "Pitch (MPH)": "92.3", "Pitch Type": "4-Seam Fastball", "mlb_id": "456715"}, {"Game Date": "2022-04-12", "Pitcher": "Bautista, Felix", "Result": "single", "EV (MPH)": "84.3", "LA (\u00b0)": "-4", "Dist (ft)": "15", "Direction": "Straightaway", "Pitch (MPH)": "97.2", "Pitch Type": "4-Seam Fastball", "mlb_id": "456715"}, {"Game Date": "2022-04-12", "Pitcher": "Akin, Keegan", "Result": "field_out", "EV (MPH)": "80.0", "LA (\u00b0)": "35", "Dist (ft)": "278", "Direction": "Straightaway", "Pitch (MPH)": "83.4", "Pitch Type": "Changeup", "mlb_id": "456715"}, {"Game Date": "2022-04-12", "Pitcher": "Watkins, Spenser", "Result": "single", "EV (MPH)": "106.6", "LA (\u00b0)": "-11", "Dist (ft)": "12", "Direction": "Straightaway", "Pitch (MPH)": "88.1", "Pitch Type": "Cutter", "mlb_id": "456715"}, {"Game Date": "2022-04-11", "Pitcher": "Perez, Cionel", "Result": "grounded_into_double_play", "EV (MPH)": "65.7", "LA (\u00b0)": "-19", "Dist (ft)": "7", "Direction": "Pull", "Pitch (MPH)": "94.2", "Pitch Type": "4-Seam Fastball", "mlb_id": "456715"}, {"Game Date": "2022-04-10", "Pitcher": "Givens, Mychal", "Result": "field_out", "EV (MPH)": "93.3", "LA (\u00b0)": "31", "Dist (ft)": "316", "Direction": "Opposite", "Pitch (MPH)": "85.5", "Pitch Type": "Slider", "mlb_id": "456715"}, {"Game Date": "2022-04-10", "Pitcher": "Norris, Daniel", "Result": "field_out", "EV (MPH)": "77.6", "LA (\u00b0)": "63", "Dist (ft)": "136", "Direction": "Straightaway", "Pitch (MPH)": "92.3", "Pitch Type": "4-Seam Fastball", "mlb_id": "456715"}, {"Game Date": "2022-04-10", "Pitcher": "Stroman, Marcus", "Result": "field_out", "EV (MPH)": "105.7", "LA (\u00b0)": "2", "Dist (ft)": "79", "Direction": "Pull", "Pitch (MPH)": "83.3", "Pitch Type": "Slider", "mlb_id": "456715"}, {"Game Date": "2022-04-10", "Pitcher": "Stroman, Marcus", "Result": "field_out", "EV (MPH)": "103.9", "LA (\u00b0)": "-8", "Dist (ft)": "14", "Direction": "Straightaway", "Pitch (MPH)": "91.3", "Pitch Type": "Sinker", "mlb_id": "456715"}, {"Game Date": "2022-04-07", "Pitcher": "Wick, Rowan", "Result": "sac_fly", "EV (MPH)": "94.0", "LA (\u00b0)": "36", "Dist (ft)": "336", "Direction": "Straightaway", "Pitch (MPH)": "75.7", "Pitch Type": "Knuckle Curve", "mlb_id": "456715"}, {"Game Date": "2022-04-07", "Pitcher": "Norris, Daniel", "Result": "double", "EV (MPH)": "105.2", "LA (\u00b0)": "8", "Dist (ft)": "217", "Direction": "Straightaway", "Pitch (MPH)": "90.8", "Pitch Type": "4-Seam Fastball", "mlb_id": "456715"}, {"Game Date": "2022-04-07", "Pitcher": "Hendricks, Kyle", "Result": "field_out", "EV (MPH)": "52.8", "LA (\u00b0)": "8", "Dist (ft)": "64", "Direction": "Opposite", "Pitch (MPH)": "86.5", "Pitch Type": "4-Seam Fastball", "mlb_id": "456715"}, {"Game Date": "2022-04-07", "Pitcher": "Hendricks, Kyle", "Result": "strikeout", "EV (MPH)": "", "LA (\u00b0)": "", "Dist (ft)": "", "Direction": "", "Pitch (MPH)": "79.7", "Pitch Type": "Changeup", "mlb_id": "456715"}]